src/__init__.py
src/client.py
src/core/__init__.py
src/core/api_error.py
src/core/datetime_utils.py
src/core/jsonable_encoder.py
src/core/remove_none_from_headers.py
src/environment.py
src/errors/__init__.py
src/errors/bad_request_error.py
src/errors/unprocessable_entity_error.py
src/resources/__init__.py
src/resources/activity/__init__.py
src/resources/activity/client.py
src/resources/body/__init__.py
src/resources/body/client.py
src/resources/devices/__init__.py
src/resources/devices/client.py
src/resources/insurance/__init__.py
src/resources/insurance/client.py
src/resources/lab_tests/__init__.py
src/resources/lab_tests/client.py
src/resources/link/__init__.py
src/resources/link/client.py
src/resources/meal/__init__.py
src/resources/meal/client.py
src/resources/profile/__init__.py
src/resources/profile/client.py
src/resources/providers/__init__.py
src/resources/providers/client.py
src/resources/sleep/__init__.py
src/resources/sleep/client.py
src/resources/team/__init__.py
src/resources/team/client.py
src/resources/testkit/__init__.py
src/resources/testkit/client.py
src/resources/timeseries/__init__.py
src/resources/timeseries/client.py
src/resources/user/__init__.py
src/resources/user/client.py
src/resources/vitals/__init__.py
src/resources/vitals/client.py
src/resources/workouts/__init__.py
src/resources/workouts/client.py
src/types/__init__.py
src/types/activity_v_2_in_db.py
src/types/address.py
src/types/appointment_availability_slots.py
src/types/appointment_event_status.py
src/types/appointment_provider.py
src/types/appointment_status.py
src/types/appointment_type.py
src/types/area_info.py
src/types/auth_type.py
src/types/biomarker_result.py
src/types/body_v_2_in_db.py
src/types/client_activity_response.py
src/types/client_body_response.py
src/types/client_facing_activity.py
src/types/client_facing_api_key.py
src/types/client_facing_appointment.py
src/types/client_facing_appointment_cancellation_reason.py
src/types/client_facing_appointment_event.py
vital_python_sdk_fern-0.1.0.dist-info/METADATA
vital_python_sdk_fern-0.1.0.dist-info/WHEEL
vital_python_sdk_fern-0.1.0.dist-info/RECORD
